deep/__init__.py
imdeep-0.1.dist-info/LICENSE.txt
imdeep-0.1.dist-info/METADATA
imdeep-0.1.dist-info/WHEEL
imdeep-0.1.dist-info/top_level.txt
imdeep-0.1.dist-info/RECORD
