Metadata-Version: 2.1
Name: imdeep
Version: 0.1
Summary: This is a test package by Deep
Home-page: UNKNOWN
Author: Deep
Author-email: deepd1534@gmail.com
License: UNKNOWN
Platform: UNKNOWN
Classifier: Programming Language :: Python :: 3
Classifier: License :: OSI Approved :: MIT License
Classifier: Operating System :: OS Independent
License-File: LICENSE.txt
